tomling/__init__.py
tomling/exceptions.py
tomling/reader.py
tomling/writer.py
tomling-0.1.0.dist-info/licenses/LICENSE
tomling-0.1.0.dist-info/METADATA
tomling-0.1.0.dist-info/WHEEL
tomling-0.1.0.dist-info/top_level.txt
tomling-0.1.0.dist-info/RECORD
