Metadata-Version: 2.4
Name: tomling
Version: 0.1.0
Summary: Reads and writes toml by tomling!
Author-email: devs_des1re <arjunbrij8811@gmail.com>
Maintainer-email: devs_des1re <arjunbrij8811@gmail.com>
License: Copyright (c) 2025 devs_des1re
Project-URL: Homepage, https://github.com/devs-des1re/tomling
Project-URL: Issues, https://github.com/devs-des1re/tomling/issues
Project-URL: Codecov, https://app.codecov.io/gh/devs-des1re/tomling
Keywords: app,macOS,windows,linux,flatpak
Classifier: License :: OSI Approved :: MIT License
Classifier: Development Status :: 4 - Beta
Classifier: Intended Audience :: Developers
Classifier: Operating System :: OS Independent
Classifier: Programming Language :: Python :: 3
Classifier: Programming Language :: Python :: 3.10
Classifier: Programming Language :: Python :: 3.11
Classifier: Programming Language :: Python :: 3.12
Classifier: Programming Language :: Python :: 3.13
Classifier: Programming Language :: Python :: 3.14
Classifier: Programming Language :: Python :: 3 :: Only
Classifier: Topic :: Software Development
Classifier: Topic :: Utilities
Requires-Python: >=3.10
License-File: LICENSE
Requires-Dist: pip>=21.2
Dynamic: license-file
